{
 "mean": 61.8,
 "median": 65,
 "min": 24,
 "max": 80,
 "dist": {
  "Incomplete": 4,
  "Needs work": 18,
  "Good": 23
 },
 "scores": [
  {
   "name": "Truck Parking Club - 47 Walker Way",
   "city": "Canton",
   "score": 24,
   "label": "Incomplete"
  },
  {
   "name": "Handy Pantry (3360 Crabtree Rd)",
   "city": "Lake Junaluska",
   "score": 24,
   "label": "Incomplete"
  },
  {
   "name": "Pilot Flying J Truck Care Service Center - Waynesville",
   "city": "Waynesville",
   "score": 27,
   "label": "Incomplete"
  },
  {
   "name": "Waynesville Tire Inc",
   "city": "Waynesville",
   "score": 27,
   "label": "Incomplete"
  },
  {
   "name": "McDowell County Rest Area I-40 Eastbound (MM 82)",
   "city": "Marion",
   "score": 43,
   "label": "Needs work"
  },
  {
   "name": "McDowell County Rest Area I-40 Westbound (MM 82)",
   "city": "Marion",
   "score": 43,
   "label": "Needs work"
  },
  {
   "name": "Studio 6 Hickory",
   "city": "Hickory",
   "score": 44,
   "label": "Needs work"
  },
  {
   "name": "Travel Store (Burma Rd)",
   "city": "Nebo",
   "score": 46,
   "label": "Needs work"
  },
  {
   "name": "Hollifields Diesel",
   "city": "Marion",
   "score": 49,
   "label": "Needs work"
  },
  {
   "name": "Truck Parking Club - 1960 US Highway 70 SE, Hickory",
   "city": "Hickory",
   "score": 53,
   "label": "Needs work"
  },
  {
   "name": "Truck Parking Club - 8814 Dietz Ave, Hickory",
   "city": "Hickory",
   "score": 53,
   "label": "Needs work"
  },
  {
   "name": "Fast Track (Hildebran)",
   "city": "Hildebran",
   "score": 53,
   "label": "Needs work"
  },
  {
   "name": "I-40 Diesel & Auto",
   "city": "Morganton",
   "score": 54,
   "label": "Needs work"
  },
  {
   "name": "Truck Parking Club - Candler lot off Smokey Park Hwy",
   "city": "Candler",
   "score": 55,
   "label": "Needs work"
  },
  {
   "name": "Asheville Weigh Station (NC State Highway Patrol)",
   "city": "Asheville",
   "score": 59,
   "label": "Needs work"
  },
  {
   "name": "Truck Parking Club - 1464 Brevard Rd lot",
   "city": "Asheville",
   "score": 59,
   "label": "Needs work"
  },
  {
   "name": "Truck Parking Club - 325 U.S. Hwy 70 SW, Hickory",
   "city": "Hickory",
   "score": 59,
   "label": "Needs work"
  },
  {
   "name": "Super 8 by Wyndham Marion NC",
   "city": "Marion",
   "score": 61,
   "label": "Needs work"
  },
  {
   "name": "McGee Commercial Tire & Service - Hickory",
   "city": "Hickory",
   "score": 62,
   "label": "Needs work"
  },
  {
   "name": "Comfort Inn Asheville East-Blue Ridge Pkwy Access",
   "city": "Asheville",
   "score": 64,
   "label": "Needs work"
  },
  {
   "name": "Days Inn & Suites by Wyndham Hickory",
   "city": "Hickory",
   "score": 64,
   "label": "Needs work"
  },
  {
   "name": "Stuckey's / Dairy Queen / Exxon of Old Fort",
   "city": "Old Fort",
   "score": 64,
   "label": "Needs work"
  },
  {
   "name": "North Carolina Welcome Center - I-40 West (Haywood County)",
   "city": "Waynesville",
   "score": 65,
   "label": "Good"
  },
  {
   "name": "Nebo Truck Stop",
   "city": "Nebo",
   "score": 68,
   "label": "Good"
  },
  {
   "name": "Snider Fleet Solutions - Hickory",
   "city": "Hickory",
   "score": 70,
   "label": "Good"
  },
  {
   "name": "Piedmont Truck Tires Inc. (McCarthy Tire Service)",
   "city": "Conover",
   "score": 70,
   "label": "Good"
  },
  {
   "name": "Vanguard Truck Centers - Conover (Hickory)",
   "city": "Conover",
   "score": 70,
   "label": "Good"
  },
  {
   "name": "Super 8 by Wyndham Black Mountain",
   "city": "Black Mountain",
   "score": 71,
   "label": "Good"
  },
  {
   "name": "Quality Inn Black Mountain-Asheville East",
   "city": "Black Mountain",
   "score": 71,
   "label": "Good"
  },
  {
   "name": "Crowne Plaza Hickory",
   "city": "Hickory",
   "score": 71,
   "label": "Good"
  },
  {
   "name": "Days Inn by Wyndham Conover-Hickory",
   "city": "Conover",
   "score": 71,
   "label": "Good"
  },
  {
   "name": "West Carolina Freightliner",
   "city": "Asheville",
   "score": 72,
   "label": "Good"
  },
  {
   "name": "Walker Tire (Bill Walker Tire Centers)",
   "city": "Asheville",
   "score": 72,
   "label": "Good"
  },
  {
   "name": "TA Candler (TravelCenters of America #221)",
   "city": "Candler",
   "score": 75,
   "label": "Good"
  },
  {
   "name": "Pilot Travel Center #393",
   "city": "Waynesville",
   "score": 75,
   "label": "Good"
  },
  {
   "name": "Pilot Travel Center #1063",
   "city": "Marion",
   "score": 75,
   "label": "Good"
  },
  {
   "name": "Love's Travel Stop #308",
   "city": "Marion",
   "score": 75,
   "label": "Good"
  },
  {
   "name": "CAT Scale at TA Candler",
   "city": "Candler",
   "score": 76,
   "label": "Good"
  },
  {
   "name": "CAT Scale - Pilot Travel Center #393",
   "city": "Waynesville",
   "score": 76,
   "label": "Good"
  },
  {
   "name": "TranSource Truck & Trailer Centers - Hickory/Newton",
   "city": "Newton",
   "score": 76,
   "label": "Good"
  },
  {
   "name": "McCabe's Tire & Service",
   "city": "Morganton",
   "score": 76,
   "label": "Good"
  },
  {
   "name": "Diesel Power Truck Center",
   "city": "Candler",
   "score": 80,
   "label": "Good"
  },
  {
   "name": "TA Truck Service - Candler",
   "city": "Candler",
   "score": 80,
   "label": "Good"
  },
  {
   "name": "CAT Scale at Pilot Travel Center #1063",
   "city": "Marion",
   "score": 80,
   "label": "Good"
  },
  {
   "name": "CAT Scale at Love's Travel Stop #308",
   "city": "Marion",
   "score": 80,
   "label": "Good"
  }
 ]
}